[
    {
        "num": 1,
        "mission": "첫 번째 미션입니다."
    },
    {
        "num": 2,
        "mission": "두 번째 미션입니다."
    },
    {
        "num": 3,
        "mission": "세 번째 미션입니다."
    },
    {
        "num": 4,
        "mission": "네 번째 미션입니다."
    },
    {
        "num": 5,
        "mission": "다섯 번째 미션입니다."
    },
    {
        "num": 6,
        "mission": "여섯 번째 미션입니다."
    },
    {
        "num": 7,
        "mission": "일곱 번째 미션입니다."
    },
    {
        "num": 8,
        "mission": "여덟 번째 미션입니다."
    },
    {
        "num": 9,
        "mission": "아홉 번째 미션입니다."
    },
    {
        "num": 10,
        "mission": "열 번째 미션입니다."
    }
    
]